py_types/__init__.py
py_types-0.1.dist-info/LICENSE
py_types-0.1.dist-info/WHEEL
py_types-0.1.dist-info/METADATA
py_types-0.1.dist-info/RECORD
