Metadata-Version: 2.1
Name: py_types
Version: 0.1
Summary: typechecker
Home-page: https://github.com/Drake-Eidukas/py-types
License: UNKNOWN
Author: Drake Eidukas
Author-email: dteidukas@gmail.com
Classifier: License :: OSI Approved :: MIT License
Requires-Dist: pytest; extra == "test"
Requires-Dist: pytest-cov; extra == "test"
Provides-Extra: test
